haystack_extensions/__init__.py
haystack_extensions/components/__init__.py
haystack_extensions/components/concurrent_runner/__init__.py
haystack_extensions/components/concurrent_runner/runner.py
haystack_extensions-0.0.4.dist-info/METADATA
haystack_extensions-0.0.4.dist-info/WHEEL
haystack_extensions-0.0.4.dist-info/licenses/LICENSE
haystack_extensions-0.0.4.dist-info/RECORD
