Metadata-Version: 2.3
Name: haystack_extensions
Version: 0.0.4
Summary: An set of useful extensions for the Haystack AI library.
Project-URL: Documentation, https://github.com/Redna/haystack-extensions#readme
Project-URL: Issues, https://github.com/Redna/haystack-extensions/issues
Project-URL: Source, https://github.com/Redna/haystack-extensions/tree/main/integrations/amazon_bedrock
Author-email: Alexander Gruhl <gruhl.alexander@gmail.com>
License-Expression: Apache-2.0
License-File: LICENSE
Classifier: Development Status :: 4 - Beta
Classifier: Programming Language :: Python
Classifier: Programming Language :: Python :: 3.8
Classifier: Programming Language :: Python :: 3.9
Classifier: Programming Language :: Python :: 3.10
Classifier: Programming Language :: Python :: 3.11
Classifier: Programming Language :: Python :: 3.12
Classifier: Programming Language :: Python :: Implementation :: CPython
Classifier: Programming Language :: Python :: Implementation :: PyPy
Requires-Python: >=3.8
Requires-Dist: haystack-ai
